<?xml version="1.0"?>
<definitions>
	<definition>
		<key>text_success</key>
		<value><![CDATA[ موفقیت: بسته بندی با موفقیت نصب شد. ]]></value>
	</definition>
	<definition>
		<key>heading_title</key>
		<value><![CDATA[بسته بندی نصب]]></value>
	</definition>
	<definition>
		<key>heading_title_license</key>
		<value><![CDATA[توافقنامه مجوز بسته بندی]]></value>
	</definition>
	<definition>
		<key>heading_title_ftp</key>
		<value><![CDATA[پارامترهای دسترسی FTP]]></value>
	</definition>
	<definition>
		<key>heading_title_download</key>
		<value><![CDATA[بسته بندی در حال بارگیری]]></value>
	</definition>
	<definition>
		<key>text_preloading</key>
		<value><![CDATA[ فایل بسته بندی %فايل% دانلود خواهد شد.]]></value>
	</definition>
	<definition>
		<key>text_loading</key>
		<value><![CDATA[دانلود فایل. اندازه: %s .<br/>این ممکن است چند ثانیه بسته به نوع اتصال خود را.]]></value>
	</definition>
	<definition>
		<key>text_key_hint</key>
		<value><![CDATA[را وارد کنید کلید نصب و راه اندازی در اینجا]]></value>
	</definition>
	<definition>
		<key>text_ftp_user</key>
		<value><![CDATA[ FTP نام كاربري: ]]></value>
	</definition>
	<definition>
		<key>text_ftp_password</key>
		<value><![CDATA[ FTP رمز عبور: ]]></value>
	</definition>
	<definition>
		<key>text_ftp_host</key>
		<value><![CDATA[ FTP هاست:]]></value>
	</definition>
	<definition>
		<key>text_i_agree</key>
		<value><![CDATA[ من به مجوز موافق ]]></value>
	</definition>
	<definition>
		<key>text_agree</key>
		<value><![CDATA[ موافقم ]]></value>
	</definition>
	<definition>
		<key>text_retry</key>
		<value><![CDATA[ دوباره امتحان کنید ]]></value>
	</definition>
	<definition>
		<key>text_disagree</key>
		<value><![CDATA[ مخالفم ]]></value>
	</definition>
	<definition>
		<key>text_download_error</key>
		<value><![CDATA[ ما متاسفیم، اما در روند آپلود خطاهای فایل رخ داده است.</br>سعی کنید یک بار دیگر.</br>اگر مشکل ادامه دانلود فایل در تاریخ سفارش خود را و نصب دستی. ]]></value>
	</definition>
	<definition>
		<key>text_continue</key>
		<value><![CDATA[ ادامه ]]></value>
	</definition>
	<definition>
		<key>text_disclaimer_heading</key>
		<value><![CDATA[ سلب مسئولیت]]></value>
	</definition>
	<definition>
		<key>text_disclaimer</key>
		<value><![CDATA[ <h3>مشتری AbanteCart عزیز,</h3><br>
شما در مورد نصب افزونه شخص ثالث به AbanteCart خود هستند
<br><br>
لطفا خواندن و درک این سلب درباره گسترش شخص ثالث است که شما در مورد نصب
<br><br>
سوند شخص ثالث و خدمات توسط فروشندگان شخص ثالث ارائه شده است.
<br><br>
اگر چه، AbanteCart اعتبار کیفیت پسوند و خدمات ارائه شده توسط شخص ثالث، AbanterCart می کند گارانتی که همه کار توسعه شخص ثالث به درستی و یا هیچ درگیری در سیستم ایجاد نمی نیست.
AbanteCart عضو و وابسته به هیچ وجه مسئول یا مسئول ادعاهای مربوط به ساخته شده به محصولات و یا خدمات ارائه شده توسط فروشندگان شخص ثالث می باشد. AbanteCart می کند کیفیت از پسوند شخص ثالث و یا خدمات را تضمین نمی کند. لطفا سوالات خود را در مورد پسوند شخص ثالث و یا خدمات به فروشنده مناسب شخص ثالث مستقیم.
اگر شما نگرانی در مورد هر ارائه دهنده شخص ثالث لطفا AbanteCart تماس

<a href="http://www.abantecart.com/contact-us" target="_blank">http://www.abantecart.com/contact-us</a><br><br>
با احترام،<br>
AbanteCart<br>
ایده آل های opensource راه حل های تجارت الکترونیک ]]></value>
	</definition>
	<definition>
		<key>warning_ftp</key>
		<value><![CDATA[ هشدار: برخی از فایل یا دایرکتوری می کند نوشتن ندارد (<span id="see_details">مشاهده همه جزئيات</span>)<br>شما می توانید این حق تغییر یا<br>استفاده از FTP دسترسی به سرور برای نصب بسته (معمولا ارائه دهنده میزبانی آن را می فرستد از طریق ایمیل)<br> ]]></value>
	</definition>
	<definition>
		<key>warning_already_installed</key>
<value><![CDATA[<p class="success">.شما در حال حاضر %فرمت% پسوند نصب! اگر می خواهید به ادامه و ارتقاء، لطفا تایید</p>]]></value>
	</definition>
	<definition>
		<key>warning_already_installed_uninstall</key>
	<value><![CDATA[شما در حال حاضر این افزونه"%ماژول ها%" نصب! اگر می خواهید اقدام به نصب مجدد، لطفا حذف و اولین حذف پسوند.]]></value>
	</definition>
	<definition>
		<key>error_pack_not_found</key>
		<value><![CDATA[ خطا: فایل بسته %بسته بندي% می کند وجود دارد نه. ]]></value>
	</definition>
	<definition>
		<key>error_repository</key>
<value><![CDATA[خطا: فایل را دانلود کنید. خطا مخزن یا کلید توسعه نامعتبر است. سعی کنید یک بار دیگر. اگر مشکل ادامه دانلود فایل در تاریخ سفارش خود را و نصب دستی. ]]></value>
	</definition>
	<definition>
		<key>error_ftp_user</key>
		<value><![CDATA[ خطا: FTP نام کاربری خالی است. ]]></value>
	</definition>
	<definition>
		<key>error_ftp_password</key>
		<value><![CDATA[ خطا: FTP رمز عبور کاربر خالی است. ]]></value>
	</definition>
	<definition>
		<key>error_ftp_connect</key>
		<value><![CDATA[ خطا: نمی تونم اتصال به FTP سرور ]]></value>
	</definition>
	<definition>
		<key>error_ftp_login</key>
		<value><![CDATA[ خطا: ورود نمی تونم به FTP سرور. نام کاربری نامعتبر است و یا رمز عبور. ]]></value>
	</definition>
	<definition>
		<key>error_ftp_path</key>
		<value><![CDATA[ خطا: نمی تونم پیدا دایرکتوری ریشه AbanteCart توسط مسیر FTP.<br>سعی کنید آن را ترک خالی برای جستجوی خودکار. ]]></value>
	</definition>
	<definition>
		<key>error_ftp_path_array</key>
	<value><![CDATA[ خطا: نمی تونم به صورت خودکار تشخیص دایرکتوری ریشه AbanteCart در FTP حالت<br>لطفا FTP مسیر درست فرم را پر کنید.<br>پیشنهادات راه هستند:  ]]></value>
	</definition>
	<definition>
		<key>error_dir_permission</key>
		<value><![CDATA[ نمی تونم به صرفه جویی در فایل به دلیل directory قابل نوشتن نیست: ]]></value>
	</definition>
	<definition>
		<key>error_package_structure</key>
		<value><![CDATA[ خطا: احتمالا بسته شکسته است. ساختار خطا بسته. ]]></value>
	</definition>
	<definition>
		<key>error_package_config</key>
		<value><![CDATA[ خطا: نمی تونم پیدا پیکربندی فایل package.xml در داخل بسته. احتمالا بسته شکسته است. ساختار خطا بسته. ]]></value>
	</definition>
	<definition>
		<key>error_package_config2</key>
		<value><![CDATA[ خطا: نمی تونم پیدا حالت نصب و راه اندازی در package.xml در داخل بسته. ]]></value>
	</definition>
	<definition>
		<key>error_package_info_not_exists</key>
		<value><![CDATA[ خطا: نمی تونم پیدا اطلاعات جلسه بسته در مورد این دانلود. ]]></value>
	</definition>
	<definition>
		<key>error_unpack</key>
		<value><![CDATA[ خطا: نمی تونم بسته باز کردن "%بسته بندي%" پس از دانلود. خطا بایگانی. مشاهده ورود به خطا برای جزئیات بیشتر. ]]></value>
	</definition>
	<definition>
		<key>error_move</key>
		<value><![CDATA[ خطا: نمی تونم کد بسته پس از باز کردن حرکت می کند. لطفا سعی کنید چک نوشتن از دایرکتوری: ]]></value>
	</definition>
	<definition>
		<key>error_install_mode</key>
		<value><![CDATA[ خطا: نمی تونم پسوند نصب "%بسته بندي%" زیرا در حال حاضر نصب شده است. شما نیاز deinstall و برای اولین بار آن را حذف کنید و یا بسته بندی ارتقا. ]]></value>
	</definition>
	<definition>
		<key>error_install_mode2</key>
		<value><![CDATA[ خطا: نمی تونم فرمت ارتقاء "%بسته بندي%" به دلیل آن نصب نشده است. شما باید دریافت بسته برای نصب. ]]></value>
	</definition>
	<definition>
		<key>error_version_compatibility</key>
		<value><![CDATA[خطا: نمی تونم نصب بسته. نسخه سبد خرید شما <b>%نسخه فعلي%</b>. نسخه(s) <b>%نسخه%</b>  ضروري. ]]></value>
	</definition>
	<definition>
		<key>error_package_version_compatibility</key>
		<value><![CDATA[خطا: نمی تونم بسته ارتقا دهید. نسخه بسته جدیدتر در حال حاضر نصب شده است. ]]></value>
	</definition>
	<definition>
		<key>error_install</key>
		<value><![CDATA[ طا: نمی تونم نصب بسته. لطفا سیستم خطا ورود برای جزئیات بیشتر. ]]></value>
	</definition>
	<definition>
		<key>error_core_version</key>
		<value><![CDATA[ خطا: شما باید نسخه نصب AbanteCart %نسخه% .<br>این بسته ارتقا فقط برای نسخه های پایین تر از  ]]></value>
	</definition>
	<definition>
		<key>text_interrupt</key>
		<value><![CDATA[ وقفه ]]></value>
	</definition>
	<definition>
		<key>text_continue</key>
		<value><![CDATA[ ادامه]]></value>
	</definition>
	<definition>
		<key>confirm_version_incompatibility</key>
		<value><![CDATA[ کپی کنونی از این فرمت برای نسخه خود را از AbanteCart تایید نشده (v%s).<br>ساخت فرمت برای AbanteCart مشخص v%s.<br>
		این یک مشکل نیست، اما اگر شما متوجه مسائل و یا ناسازگاری، لطفا با توسعه پسوند. ]]></value>
	</definition>
	<definition>
		<key>error_move_ftp</key>
		<value><![CDATA[ خطا: نمی تونم کد بسته پس از باز کردن حرکت می کند. احتمالا مسیر FTP نادرست است.<br>همچنین، لطفا، سعی کنید برای بررسی مجوز نوشتنی از دایرکتوری: ]]></value>
	</definition>
	<definition>
		<key>text_network_install</key>
		<value><![CDATA[ نصب شبکه]]></value>
	</definition>
	<definition>
		<key>text_extension_upload</key>
		<value><![CDATA[ اپلود ماژول ]]></value>
	</definition>
	<definition>
		<key>error_archive_extension</key>
		<value><![CDATA[ خطا: فقط فایل .tar.gz پشتیبانی. ]]></value>
	</definition>
	<definition>
		<key>entry_upload_file</key>
		<value><![CDATA[ اپلود فايل: ]]></value>
	</definition>
	<definition>
		<key>entry_upload_url</key>
		<value><![CDATA[ وارد كردن لينك: ]]></value>
	</definition>
	<definition>
		<key>error_move_backup</key>
		<value><![CDATA[ هشدار:فایل های پشتیبان نمی تونم قبل از ارتقا دهید. بررسی مجوز نوشتنی از دایرکتوری: ]]></value>
	</definition>
	<definition>
		<key>text_core_upgrade_attention</key>
		<value><![CDATA[ توجه!
AbanteCart در مورد به نسخه به روز رسانی می شود %s!
پشتیبان گیری خودکار کامل ایجاد خواهد شد. توصیه می شود به منظور تلاش برای ارتقاء در سایت آزمون اول. ]]></value>
	</definition>
	<definition>
		<key>text_upgrade_now</key>
		<value><![CDATA[ بروزرساني جديد! ]]></value>
	</definition>
</definitions>