<?xml version="1.0"?>
<definitions>
  <definition>
    <key>heading_title</key>
    <value><![CDATA[گروه كاربري]]></value>
  </definition>
  <definition>
    <key>text_group</key>
    <value><![CDATA[گروه كاربري]]></value>
  </definition>
  <definition>
    <key>text_success</key>
    <value><![CDATA[موفقیت: شما گروه های کاربری اصلاح شده اند!]]></value>
  </definition>
  <definition>
    <key>text_success_group_added</key>
    <value><![CDATA[شما با موفقيت يك گروه ايجاد كرديد]]></value>
  </definition>
  <definition>
    <key>text_go_to_page</key>
    <value><![CDATA[رفتن به صفحه]]></value>
  </definition>
  <definition>
    <key>text_delete_confirm</key>
    <value><![CDATA[ ايا گروه حذف شود؟]]></value>
  </definition>
  <definition>
    <key>column_name</key>
    <value><![CDATA[نام گروه]]></value>
  </definition>
  <definition>
    <key>column_action</key>
    <value><![CDATA[اجرا]]></value>
  </definition>
  <definition>
    <key>entry_name</key>
    <value><![CDATA[نام كاربري گروه:]]></value>
  </definition>
  <definition>
    <key>column_controller</key>
    <value><![CDATA[كنترل كننده]]></value>
  </definition>
  <definition>
    <key>column_access</key>
    <value><![CDATA[دسترسي]]></value>
  </definition>
  <definition>
    <key>column_modify</key>
    <value><![CDATA[تغيير دادن]]></value>
  </definition>
  <definition>
    <key>error_permission</key>
    <value><![CDATA[هشدار: شما اجازه دسترسی به تغییر گروه های کاربری نداريد!]]></value>
  </definition>
  <definition>
    <key>error_name</key>
    <value><![CDATA[نام گروه بايد بين 2 تا 32 كاراكتر باشد]]></value>
  </definition>
  <definition>
    <key>error_user</key>
    <value><![CDATA[هشدار اين گروه نميتواند به علت داشتن كاربر حذف شود %s كاربر!]]></value>
  </definition>
</definitions>
